{
  "db_name": "PostgreSQL",
  "query": "\n            UPDATE post\n            SET \n                title = $1, \n                description = $2, \n                preview_image_url = $3, \n                content = $4, \n                published_time = $5\n            WHERE id = $6\n            ",
  "describe": {
    "columns": [],
    "parameters": {
      "Left": [
        "Text",
        "Text",
        "Text",
        "Text",
        "Timestamp",
        "Int4"
      ]
    },
    "nullable": []
  },
  "hash": "d0867ba2857fedcdc9a754d0394c4f040d559118d0b9f8b6f4dcd6e6fde5d381"
}
